cai_manas/__init__.py
cai_manas/part_of_speech/__init__.py
cai_manas/part_of_speech/pos_fine_tuning.py
cai_manas/part_of_speech/pos_tagger.py
cai_manas/part_of_speech/pos_fine_tuning.config/config.yaml
cai_manas/part_of_speech/pos_fine_tuning.config/data/default.yaml
cai_manas/part_of_speech/pos_fine_tuning.config/data/part-of-speech-intrasyllabic-olive.yaml
cai_manas/part_of_speech/pos_fine_tuning.config/data/part-of-speech-olive.yaml
cai_manas/part_of_speech/pos_fine_tuning.config/model/albert-olive-cormorant-intermediate.yaml
cai_manas/part_of_speech/pos_fine_tuning.config/model/albert-olive-cormorant.yaml
cai_manas/part_of_speech/pos_fine_tuning.config/training/frequent_logs.yaml
cai_manas/tokenizer/__init__.py
cai_manas/tokenizer/cai_tokenizer_mixin.py
cai_manas/tokenizer/tokenizer.py
compassionai_manas-0.2.2.dist-info/LICENSE
compassionai_manas-0.2.2.dist-info/METADATA
compassionai_manas-0.2.2.dist-info/WHEEL
compassionai_manas-0.2.2.dist-info/top_level.txt
compassionai_manas-0.2.2.dist-info/RECORD
