Metadata-Version: 2.1
Name: compassionai-manas
Version: 0.2.2
Summary: CompassionAI Project Manas - a bidirectional Tibetan transformer
Home-page: https://github.com/compassionai/manas
Author: CompassionAI
Author-email: contact@compassion-ai.org
Project-URL: Bug Tracker, https://github.com/compassionai/issues
Classifier: Intended Audience :: Science/Research
Classifier: License :: OSI Approved :: GNU General Public License v3 (GPLv3)
Classifier: Programming Language :: Python :: 3.6
Classifier: Topic :: Scientific/Engineering :: Artificial Intelligence
Requires-Python: >=3.6
License-File: LICENSE
Requires-Dist: torch (>=1.12.1)
Requires-Dist: transformers (==4.23.1)
Requires-Dist: sentencepiece (>=0.1.96)
Requires-Dist: scikit-learn (>=1.1.2)
Requires-Dist: hydra-core (>=1.2.0)
Requires-Dist: protobuf (<=3.20.3)
